pyml_cli/__init__.py
pyml_cli/version.py
pyml_cli/cli/__init__.py
pyml_cli/cli/project.py
pyml_cli/cli/system.py
pyml_cli/templates/project/cookiecutter.json
pyml_cli/templates/project/{{ cookiecutter.__repo_name }}/.bumpversion.toml
pyml_cli/templates/project/{{ cookiecutter.__repo_name }}/.gitignore
pyml_cli/templates/project/{{ cookiecutter.__repo_name }}/.pre-commit-config.yaml
pyml_cli/templates/project/{{ cookiecutter.__repo_name }}/MANIFEST.in
pyml_cli/templates/project/{{ cookiecutter.__repo_name }}/README.md
pyml_cli/templates/project/{{ cookiecutter.__repo_name }}/mkdocs.yaml
pyml_cli/templates/project/{{ cookiecutter.__repo_name }}/pyproject.toml
pyml_cli/templates/project/{{ cookiecutter.__repo_name }}/.devcontainer/Dockerfile
pyml_cli/templates/project/{{ cookiecutter.__repo_name }}/.devcontainer/devcontainer.json
pyml_cli/templates/project/{{ cookiecutter.__repo_name }}/.github/copilot-instructions.md
pyml_cli/templates/project/{{ cookiecutter.__repo_name }}/.github/dependabot.yml
pyml_cli/templates/project/{{ cookiecutter.__repo_name }}/.github/workflows/code-style.yaml
pyml_cli/templates/project/{{ cookiecutter.__repo_name }}/.github/workflows/docs.yaml
pyml_cli/templates/project/{{ cookiecutter.__repo_name }}/.github/workflows/pr-tests.yaml
pyml_cli/templates/project/{{ cookiecutter.__repo_name }}/.github/workflows/release-pypi-package.yaml
pyml_cli/templates/project/{{ cookiecutter.__repo_name }}/docs/api.md
pyml_cli/templates/project/{{ cookiecutter.__repo_name }}/docs/apidocs.css
pyml_cli/templates/project/{{ cookiecutter.__repo_name }}/docs/config.js
pyml_cli/templates/project/{{ cookiecutter.__repo_name }}/docs/index.md
pyml_cli/templates/project/{{ cookiecutter.__repo_name }}/notebooks/marimo_nb.py
pyml_cli/templates/project/{{ cookiecutter.__repo_name }}/scripts/app.py
pyml_cli/templates/project/{{ cookiecutter.__repo_name }}/{{ cookiecutter.__module_name }}/__init__.py
pyml_cli-0.1.11.dist-info/METADATA
pyml_cli-0.1.11.dist-info/WHEEL
pyml_cli-0.1.11.dist-info/entry_points.txt
pyml_cli-0.1.11.dist-info/top_level.txt
pyml_cli-0.1.11.dist-info/RECORD
