Metadata-Version: 2.4
Name: pyml-cli
Version: 0.1.11
Requires-Python: >=3.10
Requires-Dist: matplotlib
Requires-Dist: pandas
Requires-Dist: scikit-learn
Requires-Dist: numpy
Requires-Dist: pyprojroot
Requires-Dist: scipy
Requires-Dist: pymc
Requires-Dist: seaborn
Requires-Dist: python-dotenv
Requires-Dist: typer
Requires-Dist: jax
Requires-Dist: sh
Requires-Dist: loguru
Requires-Dist: ruamel-yaml
Requires-Dist: cookiecutter
Requires-Dist: pyyaml
